week0/Verilog Simulation/rtl/full_adder.v
module full_adder(a_in, b_in, c_in, sum_out, carry_out);

   input a_in,b_in,c_in;
	 output sum_out,carry_out;

	 assign sum_out=a_in^b_in^c_in;
	 assign carry_out=a_in&b_in | b_in&c_in | a_in&c_in;

endmodule

week0/Verilog Simulation/tb/full_adder_tb.v
module full_adder_tb();
		
   //Testbench global variables
   reg   a,b,cin;
   wire  sum,carry;

   //Variable for loop iteration 
   integer i;

   //Step1 : Instantiate the full adder with order based port mapping
   full_adder dut(.a_in(a),.b_in(b),.c_in(cin),.sum_out(sum),.carry_out(carry));
   //Process to initialize the variables at 0ns

	 initial begin
			$dumpfile("full_adder.vcd"); //A Waveform file
			$dumpvars(0,full_adder_tb);//Waveform should come from Tb
	 end

   initial 
      begin
         a   = 1'b0;
	       b   = 1'b0;
			   cin = 1'b0;
      end
				
   //Process to generate stimulus using for loop
   initial
      begin 
	 for (i=0;i<8;i=i+1)
	    begin
	       {a,b,cin}=i;
	       #10;
	    end
   end
				
   //Process to monitor the changes in the variables
   initial 
      $monitor("Input a=%b, b=%b, c=%b, Output sum =%b, carry=%b",a,b,cin,sum,carry);
									
   //Process to terminate simulation after 100ns
   initial #80 $finish;
			
   
endmodule

week0/Verilog Simulation/full_adder.vcd
$date
	Sat Sep 20 18:49:59 2025
$end
$version
	Icarus Verilog
$end
$timescale
	1s
$end
$scope module full_adder_tb $end
$var wire 1 ! sum $end
$var wire 1 " carry $end
$var reg 1 # a $end
$var reg 1 $ b $end
$var reg 1 % cin $end
$var integer 32 & i [31:0] $end
$scope module dut $end
$var wire 1 # a_in $end
$var wire 1 $ b_in $end
$var wire 1 % c_in $end
$var wire 1 " carry_out $end
$var wire 1 ! sum_out $end
$upscope $end
$upscope $end
$enddefinitions $end
#0
$dumpvars
b0 &
0%
0$
0#
0"
0!
$end
#10
1!
1%
b1 &
#20
1!
1$
0%
b10 &
#30
1"
0!
1%
b11 &
#40
0"
1!
1#
0$
0%
b100 &
#50
1"
0!
1%
b101 &
#60
1"
0!
1$
0%
b110 &
#70
1!
1%
b111 &
#80
b1000 &
